LICENSE
MANIFEST.in
README.md
README.rst
setup.cfg
setup.py
exileui/__init__.py
exileui/admin.py
exileui/forms.py
exileui/urls.py
exileui/views.py
exileui/widgets.py
exileui.egg-info/PKG-INFO
exileui.egg-info/SOURCES.txt
exileui.egg-info/dependency_links.txt
exileui.egg-info/top_level.txt
exileui/static/admin/css/base.css
exileui/static/admin/css/bootstrap.css
exileui/static/admin/css/changelists.css
exileui/static/admin/css/dashboard-ui.css
exileui/static/admin/css/dashboard.css
exileui/static/admin/css/exile-ui.css
exileui/static/admin/css/fonts.css
exileui/static/admin/css/forms.css
exileui/static/admin/css/login.css
exileui/static/admin/css/material-input.css
exileui/static/admin/css/metallic.css
exileui/static/admin/css/ripple.css
exileui/static/admin/css/rtl.css
exileui/static/admin/css/theme.css
exileui/static/admin/css/widgets.css
exileui/static/admin/css/material-inputs/input-text.css
exileui/static/admin/css/material-inputs/radio-checkbox.css
exileui/static/admin/css/material-inputs/select.css
exileui/static/admin/css/third/materialize.css
exileui/static/admin/css/third/materialize.min.css
exileui/static/admin/fonts/LICENSE.txt
exileui/static/admin/fonts/README.txt
exileui/static/admin/fonts/pt_sans-narrow-bold-webfont.woff
exileui/static/admin/fonts/pt_sans-narrow-bold-webfont.woff2
exileui/static/admin/fonts/pt_sans-narrow-regular-webfont.woff
exileui/static/admin/fonts/pt_sans-narrow-regular-webfont.woff2
exileui/static/admin/fonts/MaterialIcons/MaterialIcons-Regular.eot
exileui/static/admin/fonts/MaterialIcons/MaterialIcons-Regular.ttf
exileui/static/admin/fonts/MaterialIcons/MaterialIcons-Regular.woff
exileui/static/admin/fonts/MaterialIcons/MaterialIcons-Regular.woff2
exileui/static/admin/images/calendar.png
exileui/static/admin/img/LICENSE
exileui/static/admin/img/README.txt
exileui/static/admin/img/calendar-icons.svg
exileui/static/admin/img/icon-addlink.svg
exileui/static/admin/img/icon-alert.svg
exileui/static/admin/img/icon-calendar.svg
exileui/static/admin/img/icon-changelink.svg
exileui/static/admin/img/icon-clock.svg
exileui/static/admin/img/icon-deletelink.svg
