Metadata-Version: 1.1
Name: exileui
Version: 0.1.9.15
Summary: A simple Django app to conduct Web-based exileui.
Home-page: https://github.com/exildev/exileui
Author: Cristian Trujillo
Author-email: cristiantrujillo@exile.com.co
License: GNU GENERAL PUBLIC LICENSE
Platform: UNKNOWN
Classifier: Environment :: Web Environment
Classifier: Framework :: Django
Classifier: Framework :: Django :: 1.10
Classifier: Framework :: Django :: 1.9
Classifier: Framework :: Django :: 1.8
Classifier: Intended Audience :: Developers
Classifier: Operating System :: OS Independent
Classifier: Programming Language :: Python
Classifier: Programming Language :: Python :: 2.7
